.gitignore
.travis.yml
CITATION.md
DESCRIPTION.rst
LICENSE
MANIFEST.in
README
README.rst
requirements.txt
setup.cfg
setup.py
docs/Makefile
docs/about.rst
docs/conf.py
docs/flownetpy.flowmodel.rst
docs/flownetpy.rst
docs/flownetpy.tests.flowmodel.rst
docs/flownetpy.tests.rst
docs/formalism.rst
docs/index.rst
docs/modules.rst
docs/_static/cc-by.pdf
docs/_static/cc-by.svg
flownetpy/__init__.py
flownetpy/flownetwork.py
flownetpy/kuramotonetwork.py
flownetpy/linearflownetwork.py
flownetpy/tools.py
flownetpy.egg-info/PKG-INFO
flownetpy.egg-info/SOURCES.txt
flownetpy.egg-info/dependency_links.txt
flownetpy.egg-info/requires.txt
flownetpy.egg-info/top_level.txt
flownetpy/flowmodel/__init__.py
flownetpy/flowmodel/kuramoto.py
flownetpy/tests/__init__.py
flownetpy/tests/test_kuramoto.py
flownetpy/tests/test_linear.py
flownetpy/tests/test_tools.py